GlideV4Zhongwenban/README.md
GlideV4Zhongwenban/__init__.py
GlideV4Zhongwenban/__main__.py
GlideV4Zhongwenban/file.epub
GlideV4Zhongwenban/index.html
GlideV4Zhongwenban/css/__init__.py
GlideV4Zhongwenban/css/annotations.css
GlideV4Zhongwenban/css/main.css
GlideV4Zhongwenban/css/normalize.css
GlideV4Zhongwenban/css/popup.css
GlideV4Zhongwenban/font/__init__.py
GlideV4Zhongwenban/font/fontello.eot
GlideV4Zhongwenban/font/fontello.svg
GlideV4Zhongwenban/font/fontello.ttf
GlideV4Zhongwenban/font/fontello.woff
GlideV4Zhongwenban/img/__init__.py
GlideV4Zhongwenban/img/annotator-glyph-sprite.png
GlideV4Zhongwenban/img/annotator-icon-sprite.png
GlideV4Zhongwenban/img/apple-touch-icon.png
GlideV4Zhongwenban/img/cancelfullscreen.png
GlideV4Zhongwenban/img/close.png
GlideV4Zhongwenban/img/fullscreen.png
GlideV4Zhongwenban/img/loader.gif
GlideV4Zhongwenban/img/menu-icon.png
GlideV4Zhongwenban/img/save.png
GlideV4Zhongwenban/img/saved.png
GlideV4Zhongwenban/img/settings-s.png
GlideV4Zhongwenban/img/settings.png
GlideV4Zhongwenban/img/star.png
GlideV4Zhongwenban/js/__init__.py
GlideV4Zhongwenban/js/epub.js
GlideV4Zhongwenban/js/epub.min.js
GlideV4Zhongwenban/js/epub.min.map
GlideV4Zhongwenban/js/hooks.min.js
GlideV4Zhongwenban/js/hooks.min.map
GlideV4Zhongwenban/js/reader.js
GlideV4Zhongwenban/js/reader.js.map
GlideV4Zhongwenban/js/reader.min.js
GlideV4Zhongwenban/js/reader.min.map
GlideV4Zhongwenban/js/hooks/__init__.py
GlideV4Zhongwenban/js/hooks/extensions/__init__.py
GlideV4Zhongwenban/js/hooks/extensions/highlight.js
GlideV4Zhongwenban/js/libs/__init__.py
GlideV4Zhongwenban/js/libs/jquery.min.js
GlideV4Zhongwenban/js/libs/localforage.min.js
GlideV4Zhongwenban/js/libs/screenfull.js
GlideV4Zhongwenban/js/libs/screenfull.min.js
GlideV4Zhongwenban/js/libs/zip.min.js
GlideV4Zhongwenban/js/plugins/__init__.py
GlideV4Zhongwenban/js/plugins/hypothesis.js
GlideV4Zhongwenban/js/plugins/search.js
glide_v4_zhongwenban-2024.3.3.0.dist-info/METADATA
glide_v4_zhongwenban-2024.3.3.0.dist-info/WHEEL
glide_v4_zhongwenban-2024.3.3.0.dist-info/entry_points.txt
glide_v4_zhongwenban-2024.3.3.0.dist-info/top_level.txt
glide_v4_zhongwenban-2024.3.3.0.dist-info/RECORD
